panzerspiel/__init__.py
panzerspiel/animated_sprite.py
panzerspiel/animator.py
panzerspiel/arena.py
panzerspiel/box.py
panzerspiel/button.py
panzerspiel/collision.py
panzerspiel/controller.py
panzerspiel/event_definitions.py
panzerspiel/game_scene.py
panzerspiel/global_settings.py
panzerspiel/h_slider.py
panzerspiel/health_bar.py
panzerspiel/line.py
panzerspiel/main.py
panzerspiel/menu.py
panzerspiel/menu_list.py
panzerspiel/own_sprite.py
panzerspiel/tank.py
panzerspiel/tank_config.py
panzerspiel/textbox.py
panzerspiel/vector.py
panzerspiel/res2/TBack.jpg
panzerspiel/res2/TBack.png
panzerspiel/res2/TBoxStone.png
panzerspiel/res2/TBoxWood.png
panzerspiel/res2/TCover.png
panzerspiel/res2/TCustom.png
panzerspiel/res2/TFrameBlue.png
panzerspiel/res2/TFrameRed.png
panzerspiel/res2/THealthbar.png
panzerspiel/res2/TKnob.png
panzerspiel/res2/TLeave.png
panzerspiel/res2/TOptions.png
panzerspiel/res2/TReload.png
panzerspiel/res2/TRetry.png
panzerspiel/res2/TSlider.png
panzerspiel/res2/TStart.png
panzerspiel/res2/TTankBlue.png
panzerspiel/res2/TTankMapGreen.png
panzerspiel/res2/TTankRed.png
panzerspiel/res2/explosion.mp3
panzerspiel/res2/explosion.png
panzerspiel/res2/explosion.wav
panzerspiel/res2/tank1_won.png
panzerspiel/res2/tank2_won.png
panzerspiel/res2/music/mindmapthat_-_Transmutation.mp3
Panzerspiel-1.0.dist-info/LICENCE.code
Panzerspiel-1.0.dist-info/METADATA
Panzerspiel-1.0.dist-info/WHEEL
Panzerspiel-1.0.dist-info/entry_points.txt
Panzerspiel-1.0.dist-info/top_level.txt
Panzerspiel-1.0.dist-info/RECORD
