Metadata-Version: 2.1
Name: Panzerspiel
Version: 1.0
Summary: A small 2D tank game
Home-page: UNKNOWN
License: GNU General Public License v3.0
Platform: UNKNOWN
Requires-Dist: pygame
